deta_personal_interface/__init__.py
deta_personal_interface/__main__.py
deta_personal_interface/_version.py
deta_personal_interface-0.0.1.dist-info/LICENSE
deta_personal_interface-0.0.1.dist-info/METADATA
deta_personal_interface-0.0.1.dist-info/WHEEL
deta_personal_interface-0.0.1.dist-info/top_level.txt
deta_personal_interface-0.0.1.dist-info/RECORD
