Metadata-Version: 2.1
Name: deta-personal-interface
Version: 0.0.1
Summary: Tool for teams to manage the CHANGELOG given a list of different changes.
Home-page: https://github.com/ricardoleal20/deta_personal_interface/
Author: Ricardo Leal
Author-email: ricardo.lealpz@gmail.com
Maintainer: Ricardo Leal
Maintainer-email: ricardo.lealpz@gmail.com
Project-URL: Bug Reports, https://github.com/ricardoleal20/deta_personal_interface/issues
Keywords: development,personal_usage
Classifier: Topic :: Software Development :: Build Tools
Classifier: Programming Language :: Python :: 3.8
Classifier: Programming Language :: Python :: 3.9
Classifier: Programming Language :: Python :: 3.10
Classifier: Programming Language :: Python :: 3.11
Classifier: Programming Language :: Python :: 3 :: Only
Requires-Python: >=3.8, <4
License-File: LICENSE
Requires-Dist: deta (>=1.2.0)
